richillcapital_http/__init__.py
richillcapital_http/enums.py
richillcapital_http-0.1.4.dist-info/WHEEL
richillcapital_http-0.1.4.dist-info/METADATA
richillcapital_http-0.1.4.dist-info/RECORD
