Metadata-Version: 2.1
Name: richillcapital-http
Version: 0.1.4
License: MIT
Author-email: Mengsyue Amao Tsai <mengsyue.tsai@outlook.com>
Requires-Python: >=3.11
Requires-Dist: aiohttp>=3.8.4
Requires-Dist: asyncio>=3.4.3
